corelink/__init__.py
corelink/corelink.py
corelink/resources/Proto.py
corelink/resources/__init__.py
corelink/resources/control.py
corelink/resources/processing.py
corelink/resources/reqs.py
corelink/resources/variables.py
corelink_client-0.0.7.dist-info/METADATA
corelink_client-0.0.7.dist-info/WHEEL
corelink_client-0.0.7.dist-info/licenses/LICENSE
corelink_client-0.0.7.dist-info/RECORD
