Metadata-Version: 2.3
Name: corelink-client
Version: 0.0.7
Summary: Client for connecting to Corelink server.
Project-URL: Homepage, https://corelink.hpc.nyu.edu
Author-email: Kaiwen Guo <kg3354@nyu.edu>
License: MIT License
License-File: LICENSE
Classifier: License :: OSI Approved :: MIT License
Classifier: Operating System :: OS Independent
Classifier: Programming Language :: Python :: 3
Requires-Python: >=3.7
Requires-Dist: websockets
